CHANGELOG.rst
CONTRIBUTING.md
LICENSE
pyproject.toml
README.rst
dobson/__init__.py
dobson/main.py
dobson/py.typed
dobson-0.0.1.dist-info/LICENSE
dobson-0.0.1.dist-info/METADATA
dobson-0.0.1.dist-info/WHEEL
dobson-0.0.1.dist-info/RECORD
