Metadata-Version: 2.1
Name: dobson
Version: 0.0.1
Summary: Dobson file parser
Home-page: https://github.com/gosow9/dobson
License: AGPL-3.0-only
Keywords: python package
Author: Cedric Renda
Author-email: cedric.renda@hotmail.com
Maintainer: Cedric Renda
Maintainer-email: cedric.renda@hotmail.com
Requires-Python: >=3.9,<4.0
Classifier: Development Status :: 5 - Production/Stable
Classifier: Intended Audience :: Developers
Classifier: Intended Audience :: End Users/Desktop
Classifier: Intended Audience :: Science/Research
Classifier: License :: OSI Approved :: GNU Affero General Public License v3
Classifier: Natural Language :: English
Classifier: Operating System :: MacOS
Classifier: Operating System :: POSIX :: Linux
Classifier: Operating System :: Unix
Classifier: Programming Language :: Python
Classifier: Programming Language :: Python :: 3
Classifier: Programming Language :: Python :: 3.9
Classifier: Programming Language :: Python :: 3.10
Classifier: Programming Language :: Python :: 3.11
Classifier: Topic :: Software Development
Classifier: Topic :: Software Development :: Libraries :: Python Modules
Classifier: Topic :: System :: Software Distribution
Classifier: Typing :: Typed
Provides-Extra: docs
Provides-Extra: test
Provides-Extra: typing
Requires-Dist: mypy (==0.961) ; extra == "typing"
Requires-Dist: pandas (>=2.0.3,<3.0.0)
Requires-Dist: pytest (>=6.2.4) ; extra == "test" or extra == "typing"
Requires-Dist: pytest-cov (>=2.12) ; extra == "test"
Requires-Dist: pytest-explicit (>=1.0.1,<1.1.0) ; extra == "test"
Requires-Dist: pytest-xdist (>=1.34) ; extra == "test"
Requires-Dist: sphinx (>=4.0,<5.0) ; extra == "docs"
Requires-Dist: sphinx-autodoc-typehints (>=1.10) ; extra == "docs"
Requires-Dist: sphinx-rtd-theme (==0.5.0) ; extra == "docs"
Requires-Dist: sphinxcontrib-spelling (>=7.3.3,<7.4.0) ; extra == "docs"
Project-URL: Bug Tracker, https://github.com/dobson/issues
Project-URL: CI: Github Actions, https://github.com/gosow9/dobson/actions
Project-URL: Changelog, https://github.com/gosow9/dobson/blob/master/CHANGELOG.rst
Project-URL: Code of Conduct, https://github.com/gosow9/dobson/blob/master/CONTRIBUTING.rst
Project-URL: Documentation, https://dobson.readthedocs.io/
Project-URL: Repository, https://github.com/gosow9/dobson
Project-URL: Source Code, https://github.com/gosow9/dobson
